web3socket/__init__.py
web3socket/policyserver.py
web3socket/server.py
web3socket-0.1.4.dist-info/LICENSE
web3socket-0.1.4.dist-info/METADATA
web3socket-0.1.4.dist-info/WHEEL
web3socket-0.1.4.dist-info/top_level.txt
web3socket-0.1.4.dist-info/RECORD
